AUTHORS.rst
CONTRIBUTING.rst
HISTORY.rst
LICENSE
MANIFEST.in
README.rst
setup.cfg
setup.py
docs/Makefile
docs/authors.rst
docs/conf.py
docs/contributing.rst
docs/history.rst
docs/index.rst
docs/installation.rst
docs/make.bat
docs/readme.rst
docs/usage.rst
system_monitor/__init__.py
system_monitor/default_settings.py
system_monitor/error_reporter.py
system_monitor/failure_manager.py
system_monitor/failure_manager_based_on_db.py
system_monitor/recoverable_monitor.py
system_monitor/system_monitor.py
system_monitor.egg-info/PKG-INFO
system_monitor.egg-info/SOURCES.txt
system_monitor.egg-info/dependency_links.txt
system_monitor.egg-info/entry_points.txt
system_monitor.egg-info/not-zip-safe
system_monitor.egg-info/requires.txt
system_monitor.egg-info/top_level.txt
tests/__init__.py
tests/test_system_monitor.py