Metadata-Version: 1.1
Name: system-monitor
Version: 0.1.0
Summary: A system monitor Django app based on pinax event log.
Home-page: https://github.com/weijia/system_monitor
Author: Wang Richard
Author-email: richardwangwang@gmail.com
License: MIT license
Keywords: system_monitor
Platform: UNKNOWN
Classifier: Development Status :: 2 - Pre-Alpha
Classifier: Intended Audience :: Developers
Classifier: License :: OSI Approved :: MIT License
Classifier: Natural Language :: English
Classifier: Programming Language :: Python :: 2
Classifier: Programming Language :: Python :: 2.7
Classifier: Programming Language :: Python :: 3
Classifier: Programming Language :: Python :: 3.4
Classifier: Programming Language :: Python :: 3.5
Classifier: Programming Language :: Python :: 3.6
Classifier: Programming Language :: Python :: 3.7
